_ruptura.cpython-311-darwin.so
ruptura/__init__.py
ruptura/bindings.cpp
ruptura/breakthrough.cpp
ruptura/breakthrough.h
ruptura/compile.bat
ruptura/component.cpp
ruptura/component.h
ruptura/fitting.cpp
ruptura/fitting.h
ruptura/hash_combine.h
ruptura/inputreader.cpp
ruptura/inputreader.h
ruptura/isotherm.cpp
ruptura/isotherm.h
ruptura/main.cpp
ruptura/makefile
ruptura/mixture_prediction.cpp
ruptura/mixture_prediction.h
ruptura/multi_site_isotherm.cpp
ruptura/multi_site_isotherm.h
ruptura/random_numbers.cpp
ruptura/random_numbers.h
ruptura/ruptura.exe
ruptura/ruptura.py
ruptura/special_functions.cpp
ruptura/special_functions.h
ruptura/utils.py
ruptura-1.0.4.dist-info/LICENSE.md
ruptura-1.0.4.dist-info/METADATA
ruptura-1.0.4.dist-info/WHEEL
ruptura-1.0.4.dist-info/top_level.txt
ruptura-1.0.4.dist-info/RECORD
