Metadata-Version: 2.1
Name: ruptura
Version: 1.0.4
Author: Shrinjay Sharma, Delft University of Technology, The Netherlands, Youri Ran, University of Amsterdam, The Netherlands, Salvador R.G. Balestra, Pablo de Olavide University, Spain, Richard Baur, Shell Global Solutions International B.V., The Netherlands, Umang Agarwal, Shell Global Solutions International B.V., The Netherlands, Eric Zuidema, Shell Global Solutions International B.V., The Netherlands, Marcello Rigutto, Shell Global Solutions International B.V., The Netherlands, Sofia Calero
Requires-Python: >=3.10
License-File: LICENSE.md
Requires-Dist: matplotlib >=3
Requires-Dist: numpy >=1
Requires-Dist: pybind11 >=2
Requires-Dist: setuptools >=42
